[
  {
    "id": "classic-01",
    "title": "Radetzky March Op 228",
    "artist": "Budapest Art Orchestra",
    "genre": "클래식",
    "time": "3:00",
    "audioSrc": "pages/browse/audio/Budapest Art Orchestra - Radetzky March Op 228.mp3"
  },
  {
    "id": "classic-02",
    "title": "House of Secrets",
    "artist": "Francesco DAndrea",
    "genre": "클래식",
    "time": "3:00",
    "audioSrc": "pages/browse/audio/Francesco DAndrea - House of Secrets.mp3"
  },
  {
    "id": "classic-03",
    "title": "Te Deum",
    "artist": "Yuval Shapiro",
    "genre": "클래식",
    "time": "3:00",
    "audioSrc": "pages/browse/audio/Yuval  Shapiro - Te Deum.mp3"
  },
  {
    "id": "kpop-01",
    "title": "All Is My Time",
    "artist": "Lemon",
    "genre": "케이팝",
    "time": "3:00",
    "audioSrc": "pages/browse/audio/Lemon - All Is My Time.mp3"
  },
  {
    "id": "jpop-01",
    "title": "Hoshifuru Yoruni",
    "artist": "raz",
    "genre": "제이팝",
    "time": "3:00",
    "audioSrc": "pages/browse/audio/raz - Hoshifuru Yoruni.mp3"
  },
  {
    "id": "pop-01",
    "title": "Starry Eyed",
    "artist": "Jane & The Boy",
    "genre": "팝",
    "time": "3:00",
    "audioSrc": "pages/browse/audio/Jane  The Boy - Starry Eyed.mp3"
  },
  {
    "id": "pop-02",
    "title": "9 Lives",
    "artist": "Anna Stefanie",
    "genre": "팝",
    "time": "3:00",
    "audioSrc": "pages/browse/audio/Anna Stefanie - 9 Lives.mp3"
  },
  {
    "id": "indie-band-01",
    "title": "Falling for the Crown",
    "artist": "IamDayLight",
    "genre": "인디/밴드",
    "time": "3:00",
    "audioSrc": "pages/browse/audio/IamDayLight - Falling for the Crown.mp3"
  },
  {
    "id": "indie-band-02",
    "title": "We Had a Moment",
    "artist": "SOURWAH",
    "genre": "인디/밴드",
    "time": "3:00",
    "audioSrc": "pages/browse/audio/SOURWAH - We Had a Moment.mp3"
  },
  {
    "id": "indie-band-03",
    "title": "Slowly Sinking",
    "artist": "two close",
    "genre": "인디/밴드",
    "time": "3:00",
    "audioSrc": "pages/browse/audio/two close - Slowly Sinking.mp3"
  },
  {
    "id": "hiphop-rnb-01",
    "title": "There for You",
    "artist": "call me joseph",
    "genre": "힙합/R&B",
    "time": "3:00",
    "audioSrc": "pages/browse/audio/call me joseph - there for you.mp3"
  },
  {
    "id": "hiphop-rnb-02",
    "title": "Roll the Dice",
    "artist": "Cruella",
    "genre": "힙합/R&B",
    "time": "3:00",
    "audioSrc": "pages/browse/audio/Cruella - Roll the Dice.mp3"
  },
  {
    "id": "hiphop-rnb-03",
    "title": "Machine",
    "artist": "FLAMEBOY",
    "genre": "힙합/R&B",
    "time": "3:00",
    "audioSrc": "pages/browse/audio/FLAMEBOY - Machine.mp3"
  },
  {
    "id": "hiphop-rnb-04",
    "title": "TOO EZ",
    "artist": "Frank Bentley",
    "genre": "힙합/R&B",
    "time": "3:00",
    "audioSrc": "pages/browse/audio/Frank Bentley - TOO EZ.mp3"
  },
  {
    "id": "kpop-02",
    "title": "Because of You",
    "artist": "Msick",
    "genre": "케이팝",
    "time": "3:00",
    "audioSrc": "pages/browse/audio/Msick - Because of You.mp3"
  },
  {
    "id": "kpop-03",
    "title": "Play No Games",
    "artist": "Henry Young",
    "genre": "케이팝",
    "time": "3:00",
    "audioSrc": "pages/browse/audio/Henry Young - Play No Games.mp3"
  },
  {
    "id": "jpop-02",
    "title": "Boku to Tokyo",
    "artist": "zomap",
    "genre": "제이팝",
    "time": "3:00",
    "audioSrc": "pages/browse/audio/zomap - Boku to Tokyo.mp3"
  },
  {
    "id": "jpop-03",
    "title": "You",
    "artist": "macaroom",
    "genre": "제이팝",
    "time": "3:00",
    "audioSrc": "pages/browse/audio/macaroom - You.mp3"
  },
  {
    "id": "pop-03",
    "title": "Hypnotic",
    "artist": "Jane & The Boy",
    "genre": "팝",
    "time": "3:00",
    "audioSrc": "pages/browse/audio/Jane  The Boy - Hypnotic.mp3"
  }
]
